[
    { "id":1,	
	  "nombrecomun":"tito el barbero",
	  "revisado":"10/23/1991",
	  "videoUrl":"https://www.youtube.com/embed/rWq_-AexyAo", 
	  "quien":{"socialHandle":{"tt":"@tito", "fbk":"", "igrm":"@tito_en_insta", "phn":""}, 
	           "fotoSrc":["imagenes/profile/bob301a.jpg", "imagenes/profile/bob301b.jpg", "imagenes/profile/bob301c.jpg", "imagenes/profile/bob301d.jpg", "imagenes/profile/bob301e.jpg"]
	          },
	  "cuando":{"lun":"libre", "mar":"por la tarde", "mier":"8am-11am", "jue":"3pm-11pm", "vier":"libre papi, hoy se bebe", "sab":"tambien bebo hoy", "dom":"desde 7pm"},
	  "que":["barbero", "estilista", "hair professional", "peinador", "peluquero"],
	  "donde":["moca", "anasco", "rincon"],
	  "atucasa":true
	},
	{ "id":2,
	  "nombrecomun":"lola dona", 
	  "revisado":"07/25/1992",
	  "videoUrl":"https://www.youtube.com/embed/4KjYNuNBOBg", 
	  "quien":{"socialHandle":{"tt":"", "fbk":"lola la comelola", "igrm":"@lola_en_insta", "phn":"787 249 0002"}, 
	           "fotoSrc":["imagenes/profile/bob302a.jpg", "imagenes/profile/bob302b.jpg", "imagenes/profile/bob302c.jpg"]
	          },
	  "cuando":{"lun":"12 a 5pm", "mar":"no work martes", "mier":"10pm-1am", "jue":"5am-1pm", "vier":"10:30am a 2pm", "sab":"desde 9pm", "dom":"hasta las 15"},
	  "que":["repostera", "baker", "panadera", "dulces", "postres"],
	  "donde":["ponce", "coamo", "sabana grande"],
	  "atucasa":false
	},
    { "id":3,
	  "nombrecomun":"chucho landscaping", 
	  "revisado":"07/25/1993",
	  "videoUrl":"https://www.youtube.com/embed/0Uk5kZ5k0vY", 
	  "quien":{"socialHandle":{"tt":"@granchucho", "fbk":"chucho de jayuya", "igrm":"", "phn":"787 222 0003"}, 
	           "fotoSrc":["imagenes/profile/bob303a.jpg", "imagenes/profile/bob303b.jpg"]
	          },
	  "cuando":{"lun":"no creo, llama", "mar":"quiza", "mier":"todito el dia", "jue":"3pm-11pm", "vier":"si no llueve", "sab":"desde 9am", "dom":"24hrs"},
	  "que":["pica grama", "corta grama", "tumba yerba", "limpio patios", "trimeo palos"],
	  "donde":["moca", "las marias", "mayaguez"],
	  "atucasa":true
	},
    { "id":4,
	  "nombrecomun":"papito el bello", 
	  "revisado":"07/25/1994",
	  "videoUrl":"https://www.youtube.com/embed/AFoFxirvRKU", 
	  "quien":{"socialHandle":{"tt":"@papito", "fbk":"papito el bello", "igrm":"@papito_en_insta", "phn":"787 248 0004"}, 
	           "fotoSrc":["imagenes/profile/bob304a.jpg", "imagenes/profile/bob304b.jpg", "imagenes/profile/bob304c.jpg", "imagenes/profile/bob304d.jpg"]
	          },
	  "cuando":{"lun":"libre", "mar":"libre tambien", "mier":"8am-11am", "jue":"3pm-11pm", "vier":"hoy si que si", "sab":"desde ayer", "dom":"hasta mediodia"},
	  "que":["musico", "bailarin", "orquesta", "entretenimiento actividades", "payaso"],
	  "donde":["moca", "san german", "lares"],
	  "atucasa":true
	},
	{ "id":5,
	  "nombrecomun":"luis car wash", 
	  "revisado":"07/25/1995",
	  "videoUrl":"https://www.youtube.com/embed/L0eIqLvZlz8", 
	  "quien":{"socialHandle":{"tt":"@luis", "fbk":"luis limpia carro", "igrm":"@luis_en_insta", "phn":"787 249 0005"}, 
	           "fotoSrc":["imagenes/profile/bob305a.jpg"]
	          },
	  "cuando":{"lun":"12 a 5pm", "mar":"no work martes", "mier":"10pm-1am", "jue":"5am-1pm", "vier":"10:30am a 2pm", "sab":"desde 9pm", "dom":"hasta las 15"},
	  "que":["limpia carro", "brilla carro", "vaccum car cleaner", "car detailing", "lava carro"],
	  "donde":["yauco", "santa isabel", "sabana grande"],
	  "atucasa":true
	},
    { "id":6,
	  "nombrecomun":"cheo foto shopero", 
	  "revisado":"07/25/1996",
	  "videoUrl":"https://www.youtube.com/embed/nSYT367zBUI", 
	  "quien":{"socialHandle":{"tt":"@cheo", "fbk":"cheo mr foto", "igrm":"@cheo_en_insta", "phn":"787 222 0006"}, 
	           "fotoSrc":["imagenes/profile/bob306a.jpg", "imagenes/profile/bob306b.jpg"]
	          },
	  "cuando":{"lun":"me amanesco", "mar":"quiza", "mier":"toda la noche", "jue":"3pm pa lante", "vier":"si tengo luz", "sab":"3er turno", "dom":"24hrs"},
	  "que":["profile picture photoshop", "photoshop pictures", "foto shopeo imagenes", "caricaturas basada en foto", "experto dibujo digital"],
	  "donde":["new york", "orlando", "bayamon"],
	  "atucasa":false
	}
]
